restframework_action_permission/__init__.py
restframework_action_permission/apps.py
restframework_action_permission/management/__init__.py
restframework_action_permission/management/commands/create_anonymous_user.py
restframework_action_permission/management/commands/start_permission.py
restframework_action_permission/middleware.py
restframework_action_permission/permission.py
restframework_action_permission-1.1.6.dist-info/METADATA
restframework_action_permission-1.1.6.dist-info/WHEEL
restframework_action_permission-1.1.6.dist-info/RECORD
