Metadata-Version: 2.3
Name: restframework-action-permission
Version: 1.1.6
Summary: Action based way of handling permissions in DRF.
Keywords: Django,Django rest framework,Django restframework permission
Author: Hadi Mohseni
Author-email: hadimohseni1996@gmail.com
Requires-Python: >=3.12,<4.0
Classifier: Programming Language :: Python :: 3
Classifier: Programming Language :: Python :: 3.12
Classifier: Programming Language :: Python :: 3.13
Requires-Dist: django (>=5.1.3,<6.0.0)
Requires-Dist: djangorestframework (>=3.15.2,<4.0.0)
Project-URL: Homepage, https://github.com/Hadi-Mohseni/restframework-action-permission
